cnblogger/__init__.py
cnblogger/colors.py
cnblogger/config.py
cnblogger/logger.py
cnblogger/py.typed
cnblogger/sinks.py
cnblogger/types.py
cnblogger-0.2.1.dist-info/licenses/LICENSE
cnblogger-0.2.1.dist-info/METADATA
cnblogger-0.2.1.dist-info/WHEEL
cnblogger-0.2.1.dist-info/top_level.txt
cnblogger-0.2.1.dist-info/RECORD
