Metadata-Version: 2.4
Name: cnblogger
Version: 0.2.1
Summary: Configurable logger that writes to CLI, file, HTTP API, and optional databases via simple JSON config.
Author-email: "Mr. Clark" <geoff@cnb.llc>
License: MIT
Project-URL: Homepage, https://github.com/AznIronMan/cnblogger
Project-URL: Repository, https://github.com/AznIronMan/cnblogger.git
Keywords: logging,logger,cli,file,api,database,sqlite,mysql,postgres,mongodb
Classifier: Programming Language :: Python :: 3
Classifier: Programming Language :: Python :: 3 :: Only
Classifier: License :: OSI Approved :: MIT License
Classifier: Operating System :: OS Independent
Classifier: Topic :: System :: Logging
Requires-Python: >=3.9
License-File: LICENSE
Provides-Extra: colors
Requires-Dist: colorama>=0.4.6; extra == "colors"
Provides-Extra: api
Requires-Dist: requests>=2.31.0; extra == "api"
Provides-Extra: sqlite
Provides-Extra: mysql
Requires-Dist: pymysql>=1.1.0; extra == "mysql"
Provides-Extra: postgres
Requires-Dist: psycopg2-binary>=2.9.9; extra == "postgres"
Provides-Extra: mongo
Requires-Dist: pymongo[srv]>=4.6.0; extra == "mongo"
Provides-Extra: all
Requires-Dist: colorama>=0.4.6; extra == "all"
Requires-Dist: requests>=2.31.0; extra == "all"
Requires-Dist: pymysql>=1.1.0; extra == "all"
Requires-Dist: psycopg2-binary>=2.9.9; extra == "all"
Requires-Dist: pymongo[srv]>=4.6.0; extra == "all"
Dynamic: license-file
